[
    {
        "VehicleNo": "9413",
        "TripId": 13678453,
        "RouteNo": "144",
        "Direction": "SOUTH",
        "Destination": "METROTOWN STN",
        "Pattern": "SB1",
        "Latitude": 49.225283,
        "Longitude": -122.995683,
        "RecordedTime": "07:12:45 pm",
        "RouteMap": {
            "Href": "https://nb.translink.ca/geodata/144.kmz"
        }
    },
    {
        "VehicleNo": "9496",
        "TripId": 13678405,
        "RouteNo": "144",
        "Direction": "NORTH",
        "Destination": "SFU",
        "Pattern": "NB1",
        "Latitude": 49.277083,
        "Longitude": -122.945433,
        "RecordedTime": "07:12:16 pm",
        "RouteMap": {
            "Href": "https://nb.translink.ca/geodata/144.kmz"
        }
    },
    {
        "VehicleNo": "9525",
        "TripId": 13678426,
        "RouteNo": "144",
        "Direction": "NORTH",
        "Destination": "SFU",
        "Pattern": "NB1",
        "Latitude": 49.2274,
        "Longitude": -122.994133,
        "RecordedTime": "07:12:01 pm",
        "RouteMap": {
            "Href": "https://nb.translink.ca/geodata/144.kmz"
        }
    },
    {
        "VehicleNo": "9531",
        "TripId": 13678469,
        "RouteNo": "144",
        "Direction": "SOUTH",
        "Destination": "METROTOWN STN",
        "Pattern": "SB1",
        "Latitude": 49.262917,
        "Longitude": -122.953483,
        "RecordedTime": "07:12:46 pm",
        "RouteMap": {
            "Href": "https://nb.translink.ca/geodata/144.kmz"
        }
    }
]