[
    {
        "VehicleNo": "16026",
        "TripId": 13678308,
        "RouteNo": "144",
        "Direction": "SOUTH",
        "Destination": "METROTOWN STN",
        "Pattern": "SB1",
        "Latitude": 49.278467,
        "Longitude": -122.947483,
        "RecordedTime": "01:04:01 pm",
        "RouteMap": {
            "Href": "https://nb.translink.ca/geodata/144.kmz"
        }
    },
    {
        "VehicleNo": "9407",
        "TripId": 13678208,
        "RouteNo": "144",
        "Direction": "NORTH",
        "Destination": "SFU",
        "Pattern": "NB1",
        "Latitude": 49.225,
        "Longitude": -123.003133,
        "RecordedTime": "01:02:37 pm",
        "RouteMap": {
            "Href": "https://nb.translink.ca/geodata/144.kmz"
        }
    },
    {
        "VehicleNo": "9421",
        "TripId": 13678221,
        "RouteNo": "144",
        "Direction": "NORTH",
        "Destination": "SFU",
        "Pattern": "NB1",
        "Latitude": 49.225617,
        "Longitude": -122.994133,
        "RecordedTime": "01:04:19 pm",
        "RouteMap": {
            "Href": "https://nb.translink.ca/geodata/144.kmz"
        }
    },
    {
        "VehicleNo": "9426",
        "TripId": 13678233,
        "RouteNo": "144",
        "Direction": "NORTH",
        "Destination": "SFU",
        "Pattern": "NB1",
        "Latitude": 49.242367,
        "Longitude": -122.975133,
        "RecordedTime": "01:04:20 pm",
        "RouteMap": {
            "Href": "https://nb.translink.ca/geodata/144.kmz"
        }
    },
    {
        "VehicleNo": "9458",
        "TripId": 13678292,
        "RouteNo": "144",
        "Direction": "SOUTH",
        "Destination": "METROTOWN STN",
        "Pattern": "SB1",
        "Latitude": 49.2785,
        "Longitude": -122.912667,
        "RecordedTime": "01:04:20 pm",
        "RouteMap": {
            "Href": "https://nb.translink.ca/geodata/144.kmz"
        }
    },
    {
        "VehicleNo": "9483",
        "TripId": 13678205,
        "RouteNo": "144",
        "Direction": "NORTH",
        "Destination": "SFU",
        "Pattern": "NB1",
        "Latitude": 49.240683,
        "Longitude": -122.968067,
        "RecordedTime": "01:03:47 pm",
        "RouteMap": {
            "Href": "https://nb.translink.ca/geodata/144.kmz"
        }
    },
    {
        "VehicleNo": "9687",
        "TripId": 13678311,
        "RouteNo": "144",
        "Direction": "SOUTH",
        "Destination": "METROTOWN STN",
        "Pattern": "SB1",
        "Latitude": 49.23515,
        "Longitude": -122.9551,
        "RecordedTime": "01:04:08 pm",
        "RouteMap": {
            "Href": "https://nb.translink.ca/geodata/144.kmz"
        }
    },
    {
        "VehicleNo": "9698",
        "TripId": 13678263,
        "RouteNo": "144",
        "Direction": "SOUTH",
        "Destination": "METROTOWN STN",
        "Pattern": "SB1",
        "Latitude": 49.258983,
        "Longitude": -122.963917,
        "RecordedTime": "01:03:33 pm",
        "RouteMap": {
            "Href": "https://nb.translink.ca/geodata/144.kmz"
        }
    }
]