[
    {
        "VehicleNo": "9405",
        "TripId": 13678239,
        "RouteNo": "144",
        "Direction": "NORTH",
        "Destination": "SFU",
        "Pattern": "NB1",
        "Latitude": 49.234483,
        "Longitude": -122.956217,
        "RecordedTime": "10:23:29 am",
        "RouteMap": {
            "Href": "https://nb.translink.ca/geodata/144.kmz"
        }
    },
    {
        "VehicleNo": "9408",
        "TripId": 13678218,
        "RouteNo": "144",
        "Direction": "NORTH",
        "Destination": "SFU",
        "Pattern": "NB1",
        "Latitude": 49.27955,
        "Longitude": -122.91995,
        "RecordedTime": "10:23:14 am",
        "RouteMap": {
            "Href": "https://nb.translink.ca/geodata/144.kmz"
        }
    },
    {
        "VehicleNo": "9418",
        "TripId": 13678260,
        "RouteNo": "144",
        "Direction": "SOUTH",
        "Destination": "METROTOWN STN",
        "Pattern": "SB1",
        "Latitude": 49.249967,
        "Longitude": -122.970233,
        "RecordedTime": "10:23:38 am",
        "RouteMap": {
            "Href": "https://nb.translink.ca/geodata/144.kmz"
        }
    },
    {
        "VehicleNo": "9424",
        "TripId": 13678296,
        "RouteNo": "144",
        "Direction": "SOUTH",
        "Destination": "METROTOWN STN",
        "Pattern": "SB1",
        "Latitude": 49.234967,
        "Longitude": -122.955467,
        "RecordedTime": "10:23:27 am",
        "RouteMap": {
            "Href": "https://nb.translink.ca/geodata/144.kmz"
        }
    },
    {
        "VehicleNo": "9480",
        "TripId": 13678193,
        "RouteNo": "144",
        "Direction": "NORTH",
        "Destination": "SFU",
        "Pattern": "NB1",
        "Latitude": 49.249867,
        "Longitude": -122.970433,
        "RecordedTime": "10:23:29 am",
        "RouteMap": {
            "Href": "https://nb.translink.ca/geodata/144.kmz"
        }
    },
    {
        "VehicleNo": "9495",
        "TripId": 13678229,
        "RouteNo": "144",
        "Direction": "NORTH",
        "Destination": "SFU",
        "Pattern": "NB1",
        "Latitude": 49.26835,
        "Longitude": -122.9535,
        "RecordedTime": "10:23:33 am",
        "RouteMap": {
            "Href": "https://nb.translink.ca/geodata/144.kmz"
        }
    },
    {
        "VehicleNo": "9513",
        "TripId": 13678312,
        "RouteNo": "144",
        "Direction": "SOUTH",
        "Destination": "METROTOWN STN",
        "Pattern": "SB1",
        "Latitude": 49.235183,
        "Longitude": -122.955117,
        "RecordedTime": "10:22:19 am",
        "RouteMap": {
            "Href": "https://nb.translink.ca/geodata/144.kmz"
        }
    },
    {
        "VehicleNo": "9537",
        "TripId": 13678289,
        "RouteNo": "144",
        "Direction": "SOUTH",
        "Destination": "METROTOWN STN",
        "Pattern": "SB1",
        "Latitude": 49.27265,
        "Longitude": -122.95355,
        "RecordedTime": "10:23:24 am",
        "RouteMap": {
            "Href": "https://nb.translink.ca/geodata/144.kmz"
        }
    }
]