[
    {
        "VehicleNo": "19020",
        "TripId": 13717399,
        "RouteNo": "R5",
        "Direction": "WEST",
        "Destination": "HASTINGS ST / TO BURRARD STN",
        "Pattern": "W1",
        "Latitude": 49.274283,
        "Longitude": -122.9274,
        "RecordedTime": "02:11:55 pm",
        "RouteMap": {
            "Href": "https://nb.translink.ca/geodata/R5.kmz"
        }
    },
    {
        "VehicleNo": "19029",
        "TripId": 13717208,
        "RouteNo": "R5",
        "Direction": "EAST",
        "Destination": "HASTINGS ST / TO SFU EXCHANGE",
        "Pattern": "E1",
        "Latitude": 49.2802,
        "Longitude": -122.910717,
        "RecordedTime": "02:12:41 pm",
        "RouteMap": {
            "Href": "https://nb.translink.ca/geodata/R5.kmz"
        }
    },
    {
        "VehicleNo": "19033",
        "TripId": 13717205,
        "RouteNo": "R5",
        "Direction": "EAST",
        "Destination": "HASTINGS ST / TO SFU EXCHANGE",
        "Pattern": "E1",
        "Latitude": 49.28625,
        "Longitude": -123.11815,
        "RecordedTime": "02:11:58 pm",
        "RouteMap": {
            "Href": "https://nb.translink.ca/geodata/R5.kmz"
        }
    },
    {
        "VehicleNo": "19036",
        "TripId": 13717370,
        "RouteNo": "R5",
        "Direction": "WEST",
        "Destination": "HASTINGS ST / TO BURRARD STN",
        "Pattern": "W1",
        "Latitude": 49.280417,
        "Longitude": -122.981917,
        "RecordedTime": "02:11:58 pm",
        "RouteMap": {
            "Href": "https://nb.translink.ca/geodata/R5.kmz"
        }
    },
    {
        "VehicleNo": "22002",
        "TripId": 13717303,
        "RouteNo": "R5",
        "Direction": "WEST",
        "Destination": "HASTINGS ST / TO BURRARD STN",
        "Pattern": "W1",
        "Latitude": 49.281183,
        "Longitude": -123.0254,
        "RecordedTime": "02:12:36 pm",
        "RouteMap": {
            "Href": "https://nb.translink.ca/geodata/R5.kmz"
        }
    },
    {
        "VehicleNo": "22003",
        "TripId": 13717372,
        "RouteNo": "R5",
        "Direction": "WEST",
        "Destination": "HASTINGS ST / TO BURRARD STN",
        "Pattern": "W1",
        "Latitude": 49.28515,
        "Longitude": -123.1138,
        "RecordedTime": "02:12:35 pm",
        "RouteMap": {
            "Href": "https://nb.translink.ca/geodata/R5.kmz"
        }
    },
    {
        "VehicleNo": "22008",
        "TripId": 13717207,
        "RouteNo": "R5",
        "Direction": "EAST",
        "Destination": "HASTINGS ST / TO SFU EXCHANGE",
        "Pattern": "E1",
        "Latitude": 49.281083,
        "Longitude": -123.028533,
        "RecordedTime": "02:11:53 pm",
        "RouteMap": {
            "Href": "https://nb.translink.ca/geodata/R5.kmz"
        }
    },
    {
        "VehicleNo": "22015",
        "TripId": 13717369,
        "RouteNo": "R5",
        "Direction": "WEST",
        "Destination": "HASTINGS ST / TO BURRARD STN",
        "Pattern": "W1",
        "Latitude": 49.2785,
        "Longitude": -122.912767,
        "RecordedTime": "02:12:21 pm",
        "RouteMap": {
            "Href": "https://nb.translink.ca/geodata/R5.kmz"
        }
    },
    {
        "VehicleNo": "23002",
        "TripId": 13717206,
        "RouteNo": "R5",
        "Direction": "EAST",
        "Destination": "HASTINGS ST / TO SFU EXCHANGE",
        "Pattern": "E1",
        "Latitude": 49.281217,
        "Longitude": -123.094983,
        "RecordedTime": "02:12:36 pm",
        "RouteMap": {
            "Href": "https://nb.translink.ca/geodata/R5.kmz"
        }
    },
    {
        "VehicleNo": "23007",
        "TripId": 13717304,
        "RouteNo": "R5",
        "Direction": "WEST",
        "Destination": "HASTINGS ST / TO BURRARD STN",
        "Pattern": "W1",
        "Latitude": 49.281083,
        "Longitude": -123.083933,
        "RecordedTime": "02:12:03 pm",
        "RouteMap": {
            "Href": "https://nb.translink.ca/geodata/R5.kmz"
        }
    },
    {
        "VehicleNo": "23014",
        "TripId": 13717224,
        "RouteNo": "R5",
        "Direction": "EAST",
        "Destination": "HASTINGS ST / TO SFU EXCHANGE",
        "Pattern": "E1",
        "Latitude": 49.280283,
        "Longitude": -122.9895,
        "RecordedTime": "02:12:08 pm",
        "RouteMap": {
            "Href": "https://nb.translink.ca/geodata/R5.kmz"
        }
    },
    {
        "VehicleNo": "8133",
        "TripId": 13717418,
        "RouteNo": "R5",
        "Direction": "WEST",
        "Destination": "HASTINGS ST / TO WATERFRONT STN",
        "Pattern": "W8TL2",
        "Latitude": 49.28125,
        "Longitude": -123.067333,
        "RecordedTime": "02:12:10 pm",
        "RouteMap": {
            "Href": "https://nb.translink.ca/geodata/R5.kmz"
        }
    },
    {
        "VehicleNo": "9662",
        "TripId": 13717419,
        "RouteNo": "R5",
        "Direction": "WEST",
        "Destination": "HASTINGS ST / TO WATERFRONT STN",
        "Pattern": "W8TL2",
        "Latitude": 49.2811,
        "Longitude": -123.084333,
        "RecordedTime": "02:12:03 pm",
        "RouteMap": {
            "Href": "https://nb.translink.ca/geodata/R5.kmz"
        }
    }
]