[
    {
        "VehicleNo": "19021",
        "TripId": 13717205,
        "RouteNo": "R5",
        "Direction": "EAST",
        "Destination": "HASTINGS ST / TO SFU EXCHANGE",
        "Pattern": "E1",
        "Latitude": 49.2803,
        "Longitude": -122.97945,
        "RecordedTime": "02:50:23 pm",
        "RouteMap": {
            "Href": "https://nb.translink.ca/geodata/R5.kmz"
        }
    },
    {
        "VehicleNo": "19037",
        "TripId": 13717368,
        "RouteNo": "R5",
        "Direction": "WEST",
        "Destination": "HASTINGS ST / TO BURRARD STN",
        "Pattern": "W1",
        "Latitude": 49.276167,
        "Longitude": -122.930883,
        "RecordedTime": "02:49:22 pm",
        "RouteMap": {
            "Href": "https://nb.translink.ca/geodata/R5.kmz"
        }
    },
    {
        "VehicleNo": "19040",
        "TripId": 13717206,
        "RouteNo": "R5",
        "Direction": "EAST",
        "Destination": "HASTINGS ST / TO SFU EXCHANGE",
        "Pattern": "E1",
        "Latitude": 49.273567,
        "Longitude": -122.926,
        "RecordedTime": "02:50:16 pm",
        "RouteMap": {
            "Href": "https://nb.translink.ca/geodata/R5.kmz"
        }
    },
    {
        "VehicleNo": "19044",
        "TripId": 13717203,
        "RouteNo": "R5",
        "Direction": "EAST",
        "Destination": "HASTINGS ST / TO SFU EXCHANGE",
        "Pattern": "E1",
        "Latitude": 49.286183,
        "Longitude": -123.118317,
        "RecordedTime": "02:48:36 pm",
        "RouteMap": {
            "Href": "https://nb.translink.ca/geodata/R5.kmz"
        }
    },
    {
        "VehicleNo": "19045",
        "TripId": 13717369,
        "RouteNo": "R5",
        "Direction": "WEST",
        "Destination": "HASTINGS ST / TO BURRARD STN",
        "Pattern": "W1",
        "Latitude": 49.281283,
        "Longitude": -123.069667,
        "RecordedTime": "02:50:41 pm",
        "RouteMap": {
            "Href": "https://nb.translink.ca/geodata/R5.kmz"
        }
    },
    {
        "VehicleNo": "19046",
        "TripId": 13717207,
        "RouteNo": "R5",
        "Direction": "EAST",
        "Destination": "HASTINGS ST / TO SFU EXCHANGE",
        "Pattern": "E1",
        "Latitude": 49.27975,
        "Longitude": -122.9199,
        "RecordedTime": "02:41:20 pm",
        "RouteMap": {
            "Href": "https://nb.translink.ca/geodata/R5.kmz"
        }
    },
    {
        "VehicleNo": "22006",
        "TripId": 13717223,
        "RouteNo": "R5",
        "Direction": "EAST",
        "Destination": "HASTINGS ST / TO SFU EXCHANGE",
        "Pattern": "E1",
        "Latitude": 49.2811,
        "Longitude": -123.049583,
        "RecordedTime": "02:50:36 pm",
        "RouteMap": {
            "Href": "https://nb.translink.ca/geodata/R5.kmz"
        }
    },
    {
        "VehicleNo": "22012",
        "TripId": 13717204,
        "RouteNo": "R5",
        "Direction": "EAST",
        "Destination": "HASTINGS ST / TO SFU EXCHANGE",
        "Pattern": "E1",
        "Latitude": 49.281233,
        "Longitude": -123.073583,
        "RecordedTime": "02:50:03 pm",
        "RouteMap": {
            "Href": "https://nb.translink.ca/geodata/R5.kmz"
        }
    },
    {
        "VehicleNo": "22013",
        "TripId": 13717222,
        "RouteNo": "R5",
        "Direction": "EAST",
        "Destination": "HASTINGS ST / TO SFU EXCHANGE",
        "Pattern": "E1",
        "Latitude": 49.2823,
        "Longitude": -123.10855,
        "RecordedTime": "02:50:18 pm",
        "RouteMap": {
            "Href": "https://nb.translink.ca/geodata/R5.kmz"
        }
    },
    {
        "VehicleNo": "22015",
        "TripId": 13717301,
        "RouteNo": "R5",
        "Direction": "WEST",
        "Destination": "HASTINGS ST / TO BURRARD STN",
        "Pattern": "W1",
        "Latitude": 49.28115,
        "Longitude": -123.018183,
        "RecordedTime": "02:49:38 pm",
        "RouteMap": {
            "Href": "https://nb.translink.ca/geodata/R5.kmz"
        }
    },
    {
        "VehicleNo": "8141",
        "TripId": 13717399,
        "RouteNo": "R5",
        "Direction": "WEST",
        "Destination": "HASTINGS ST / TO BURRARD STN",
        "Pattern": "W1",
        "Latitude": 49.281967,
        "Longitude": -123.106817,
        "RecordedTime": "02:50:45 pm",
        "RouteMap": {
            "Href": "https://nb.translink.ca/geodata/R5.kmz"
        }
    },
    {
        "VehicleNo": "8154",
        "TripId": 13717408,
        "RouteNo": "R5",
        "Direction": "WEST",
        "Destination": "HASTINGS ST / TO WATERFRONT STN",
        "Pattern": "W8TL2",
        "Latitude": 49.281967,
        "Longitude": -123.106733,
        "RecordedTime": "02:50:16 pm",
        "RouteMap": {
            "Href": "https://nb.translink.ca/geodata/R5.kmz"
        }
    },
    {
        "VehicleNo": "9756",
        "TripId": 13717410,
        "RouteNo": "R5",
        "Direction": "WEST",
        "Destination": "HASTINGS ST / TO WATERFRONT STN",
        "Pattern": "W8TL2",
        "Latitude": 49.28125,
        "Longitude": -123.031183,
        "RecordedTime": "02:50:23 pm",
        "RouteMap": {
            "Href": "https://nb.translink.ca/geodata/R5.kmz"
        }
    }
]