[
    {
        "VehicleNo": "19021",
        "TripId": 13717205,
        "RouteNo": "R5",
        "Direction": "EAST",
        "Destination": "HASTINGS ST / TO SFU EXCHANGE",
        "Pattern": "E1",
        "Latitude": 49.281117,
        "Longitude": -123.0556,
        "RecordedTime": "02:32:38 pm",
        "RouteMap": {
            "Href": "https://nb.translink.ca/geodata/R5.kmz"
        }
    },
    {
        "VehicleNo": "19037",
        "TripId": 13717368,
        "RouteNo": "R5",
        "Direction": "WEST",
        "Destination": "HASTINGS ST / TO BURRARD STN",
        "Pattern": "W1",
        "Latitude": 49.278333,
        "Longitude": -122.910617,
        "RecordedTime": "02:32:28 pm",
        "RouteMap": {
            "Href": "https://nb.translink.ca/geodata/R5.kmz"
        }
    },
    {
        "VehicleNo": "19040",
        "TripId": 13717206,
        "RouteNo": "R5",
        "Direction": "EAST",
        "Destination": "HASTINGS ST / TO SFU EXCHANGE",
        "Pattern": "E1",
        "Latitude": 49.281033,
        "Longitude": -123.014833,
        "RecordedTime": "02:31:58 pm",
        "RouteMap": {
            "Href": "https://nb.translink.ca/geodata/R5.kmz"
        }
    },
    {
        "VehicleNo": "19044",
        "TripId": 13717370,
        "RouteNo": "R5",
        "Direction": "WEST",
        "Destination": "HASTINGS ST / TO BURRARD STN",
        "Pattern": "W1",
        "Latitude": 49.2814,
        "Longitude": -123.0993,
        "RecordedTime": "02:32:36 pm",
        "RouteMap": {
            "Href": "https://nb.translink.ca/geodata/R5.kmz"
        }
    },
    {
        "VehicleNo": "19045",
        "TripId": 13717369,
        "RouteNo": "R5",
        "Direction": "WEST",
        "Destination": "HASTINGS ST / TO BURRARD STN",
        "Pattern": "W1",
        "Latitude": 49.280233,
        "Longitude": -122.991,
        "RecordedTime": "02:32:23 pm",
        "RouteMap": {
            "Href": "https://nb.translink.ca/geodata/R5.kmz"
        }
    },
    {
        "VehicleNo": "19046",
        "TripId": 13717207,
        "RouteNo": "R5",
        "Direction": "EAST",
        "Destination": "HASTINGS ST / TO SFU EXCHANGE",
        "Pattern": "E1",
        "Latitude": 49.2803,
        "Longitude": -122.952633,
        "RecordedTime": "02:32:40 pm",
        "RouteMap": {
            "Href": "https://nb.translink.ca/geodata/R5.kmz"
        }
    },
    {
        "VehicleNo": "22006",
        "TripId": 13717223,
        "RouteNo": "R5",
        "Direction": "EAST",
        "Destination": "HASTINGS ST / TO SFU EXCHANGE",
        "Pattern": "E1",
        "Latitude": 49.281867,
        "Longitude": -123.106367,
        "RecordedTime": "02:32:27 pm",
        "RouteMap": {
            "Href": "https://nb.translink.ca/geodata/R5.kmz"
        }
    },
    {
        "VehicleNo": "22012",
        "TripId": 13717204,
        "RouteNo": "R5",
        "Direction": "EAST",
        "Destination": "HASTINGS ST / TO SFU EXCHANGE",
        "Pattern": "E1",
        "Latitude": 49.286183,
        "Longitude": -123.118183,
        "RecordedTime": "02:32:03 pm",
        "RouteMap": {
            "Href": "https://nb.translink.ca/geodata/R5.kmz"
        }
    },
    {
        "VehicleNo": "22013",
        "TripId": 13717303,
        "RouteNo": "R5",
        "Direction": "WEST",
        "Destination": "HASTINGS ST / TO BURRARD STN",
        "Pattern": "W1",
        "Latitude": 49.281433,
        "Longitude": -123.101333,
        "RecordedTime": "02:32:13 pm",
        "RouteMap": {
            "Href": "https://nb.translink.ca/geodata/R5.kmz"
        }
    },
    {
        "VehicleNo": "8128",
        "TripId": 13717418,
        "RouteNo": "R5",
        "Direction": "WEST",
        "Destination": "HASTINGS ST / TO WATERFRONT STN",
        "Pattern": "W8TL2",
        "Latitude": 49.282067,
        "Longitude": -123.107217,
        "RecordedTime": "02:32:13 pm",
        "RouteMap": {
            "Href": "https://nb.translink.ca/geodata/R5.kmz"
        }
    },
    {
        "VehicleNo": "8141",
        "TripId": 13717399,
        "RouteNo": "R5",
        "Direction": "WEST",
        "Destination": "HASTINGS ST / TO BURRARD STN",
        "Pattern": "W1",
        "Latitude": 49.2812,
        "Longitude": -123.02535,
        "RecordedTime": "02:32:18 pm",
        "RouteMap": {
            "Href": "https://nb.translink.ca/geodata/R5.kmz"
        }
    },
    {
        "VehicleNo": "8154",
        "TripId": 13717408,
        "RouteNo": "R5",
        "Direction": "WEST",
        "Destination": "HASTINGS ST / TO WATERFRONT STN",
        "Pattern": "W8TL2",
        "Latitude": 49.281217,
        "Longitude": -123.025767,
        "RecordedTime": "02:32:10 pm",
        "RouteMap": {
            "Href": "https://nb.translink.ca/geodata/R5.kmz"
        }
    }
]